setup.py
Pivotal_Cli.egg-info/PKG-INFO
Pivotal_Cli.egg-info/SOURCES.txt
Pivotal_Cli.egg-info/dependency_links.txt
Pivotal_Cli.egg-info/entry_points.txt
Pivotal_Cli.egg-info/not-zip-safe
Pivotal_Cli.egg-info/requires.txt
Pivotal_Cli.egg-info/top_level.txt
pivotalcli/__init__.py
pivotalcli/cli.py
pivotalcli/helpers.py