Metadata-Version: 1.0
Name: Pivotal-Cli
Version: 0.0.1
Summary: Command line client for Pivotal Tracker
Home-page: UNKNOWN
Author: Alen Mujezinovic
Author-email: alen@caffeinehit.com
License: UNKNOWN
Platform: UNKNOWN
